{"auditAuthorizationSuccess":false,"auditFilter":"{\n  \"$or\": [\n    {\n      \"users\": []\n    },\n    {\n      \"$and\": [\n        {\n          \"$or\": [\n            {\n              \"users\": {\n                \"$elemMatch\": {\n                  \"$or\": [\n                    {\n                      \"db\": \"admin\"\n                    },\n                    {\n                      \"db\": \"$external\"\n                    }\n                  ]\n                }\n              }\n            },\n            {\n              \"roles\": {\n                \"$elemMatch\": {\n                  \"$or\": [\n                    {\n                      \"db\": \"admin\"\n                    }\n                  ]\n                }\n              }\n            }\n          ]\n        },\n        {\n          \"atype\": {\n            \"$in\": [\n              \"authenticate\",\n              \"createCollection\",\n              \"createDatabase\",\n              \"createIndex\",\n              \"renameCollection\",\n              \"dropCollection\",\n              \"dropDatabase\",\n              \"dropIndex\",\n              \"createUser\",\n              \"dropUser\",\n              \"dropAllUsersFromDatabase\",\n              \"updateUser\",\n              \"grantRolesToUser\",\n              \"revokeRolesFromUser\",\n              \"createRole\",\n              \"updateRole\",\n              \"dropRole\",\n              \"dropAllRolesFromDatabase\",\n              \"grantRolesToRole\",\n              \"revokeRolesFromRole\",\n              \"grantPrivilegesToRole\",\n              \"revokePrivilegesFromRole\",\n              \"enableSharding\",\n              \"shardCollection\",\n              \"addShard\",\n              \"removeShard\",\n              \"shutdown\",\n              \"applicationMessage\"\n            ]\n          }\n        }\n      ]\n    }\n  ]\n}","configurationType":"FILTER_JSON","enabled":true}
